README.md
setup.py
starlord/__init__.py
starlord/data/__init__.py
starlord/data/dataset.py
starlord/data/embodiment_tags.py
starlord/data/schema.py
starlord/data/transform/__init__.py
starlord/data/transform/base.py
starlord/data/transform/concat.py
starlord/data/transform/state_action.py
starlord/data/transform/video.py
starlord/experiment/__init__.py
starlord/experiment/data_config.py
starlord/experiment/runner.py
starlord/experiment/trainer.py
starlord/model/__init__.py
starlord/model/gr00t_n1.py
starlord/model/policy.py
starlord/model/transforms.py
starlord/model/action_head/__init__.py
starlord/model/action_head/action_encoder.py
starlord/model/action_head/cross_attention_dit.py
starlord/model/action_head/flow_matching_action_head.py
starlord/model/backbone/__init__.py
starlord/model/backbone/eagle_backbone.py
starlord/model/backbone/namo_backbone.py
starlord/model/backbone/qwen25_vl_backbone.py
starlord/utils/__init__.py
starlord/utils/eval.py
starlord/utils/experiment.py
starlord/utils/misc.py
starlord/utils/peft.py
starlord/utils/video.py
starlord_twin.egg-info/PKG-INFO
starlord_twin.egg-info/SOURCES.txt
starlord_twin.egg-info/dependency_links.txt
starlord_twin.egg-info/top_level.txt